crypto_condor/__init__.py
crypto_condor/cli/__init__.py
crypto_condor/cli/audit.py
crypto_condor/cli/callbacks.py
crypto_condor/cli/config.py
crypto_condor/cli/main.py
crypto_condor/cli/run.py
crypto_condor/cli/test.py
crypto_condor/cli/verify.py
crypto_condor/constants.py
crypto_condor/harness.py
crypto_condor/primitives/AES.py
crypto_condor/primitives/ChaCha20.py
crypto_condor/primitives/ECDH.py
crypto_condor/primitives/ECDSA.py
crypto_condor/primitives/HMAC.py
crypto_condor/primitives/HQC.py
crypto_condor/primitives/MLDSA.py
crypto_condor/primitives/MLKEM.py
crypto_condor/primitives/Makefile
crypto_condor/primitives/RSAES.py
crypto_condor/primitives/RSASSA.py
crypto_condor/primitives/SHA.py
crypto_condor/primitives/SHAKE.py
crypto_condor/primitives/SLHDSA.py
crypto_condor/primitives/TestU01.py
crypto_condor/primitives/__init__.py
crypto_condor/primitives/_aes/AES.zip
crypto_condor/primitives/_aes/Makefile
crypto_condor/primitives/_aes/aes.c
crypto_condor/primitives/_aes/aes.h
crypto_condor/primitives/_mldsa/.gitignore
crypto_condor/primitives/_mldsa/Makefile
crypto_condor/primitives/_mldsa/README.md
crypto_condor/primitives/_mldsa/cc-mldsa-ios.patch
crypto_condor/primitives/_mldsa/cc-mldsa.patch
crypto_condor/primitives/_mldsa/dilithium/.git/HEAD
crypto_condor/primitives/_mldsa/dilithium/.git/config
crypto_condor/primitives/_mldsa/dilithium/.git/description
crypto_condor/primitives/_mldsa/dilithium/.git/hooks/applypatch-msg.sample
crypto_condor/primitives/_mldsa/dilithium/.git/hooks/commit-msg.sample
crypto_condor/primitives/_mldsa/dilithium/.git/hooks/fsmonitor-watchman.sample
crypto_condor/primitives/_mldsa/dilithium/.git/hooks/post-update.sample
crypto_condor/primitives/_mldsa/dilithium/.git/hooks/pre-applypatch.sample
crypto_condor/primitives/_mldsa/dilithium/.git/hooks/pre-commit.sample
crypto_condor/primitives/_mldsa/dilithium/.git/hooks/pre-merge-commit.sample
crypto_condor/primitives/_mldsa/dilithium/.git/hooks/pre-push.sample
crypto_condor-2025.9.8.dist-info/LICENSE
crypto_condor-2025.9.8.dist-info/METADATA
crypto_condor-2025.9.8.dist-info/WHEEL
crypto_condor-2025.9.8.dist-info/entry_points.txt
crypto_condor-2025.9.8.dist-info/RECORD
