Metadata-Version: 2.3
Name: crypto-condor
Version: 2025.9.8
Summary: Compliance testing for implementations of cryptographic primitives
License: Apache-2.0
Keywords: cryptography,compliance
Author: Julio Loayza Meneses
Author-email: jloayzameneses@quarkslab.com
Requires-Python: >=3.10,<4.0
Classifier: License :: OSI Approved :: Apache Software License
Classifier: Programming Language :: Python :: 3
Classifier: Programming Language :: Python :: 3.10
Classifier: Programming Language :: Python :: 3.11
Classifier: Programming Language :: Python :: 3.12
Classifier: Programming Language :: Python :: 3.13
Requires-Dist: attrs (>=23.1.0,<24.0.0)
Requires-Dist: cffi (>=1.16.0,<2.0.0)
Requires-Dist: cryptography (>=43.0.0,<44.0.0)
Requires-Dist: lief (>=0.16,<1.0)
Requires-Dist: protobuf (>=5.28.3,<6.0.0)
Requires-Dist: pycryptodome (>=3.17,<4.0)
Requires-Dist: strenum (>=0.4.15,<0.5.0)
Requires-Dist: typer (>=0.17.4,<0.18.0)
Project-URL: Documentation, https://quarkslab.github.io/crypto-condor/latest/index.html
Project-URL: Homepage, https://github.com/quarkslab/crypto-condor
Project-URL: Repository, https://github.com/quarkslab/crypto-condor
